[
  {
    "id": 900,
    "e_name": "イベント名",
    "e_genre": "Genre1",
    "o_name": "企画団体名",
    "area": "Area1",
    "p_name": "203"
  },
  {
    "id": 901,
    "e_name": "イベント名",
    "e_genre": "Genre2",
    "o_name": "企画団体名",
    "area": "Area1",
    "p_name": "103"
  },
  {
    "id": 901,
    "e_name": "イベント名",
    "e_genre": "Genre2",
    "o_name": "企画団体名",
    "area": "Area1",
    "p_name": "103"
  },
  {
    "id": 901,
    "e_name": "イベント名",
    "e_genre": "Genre2",
    "o_name": "企画団体名",
    "area": "Area1",
    "p_name": "103"
  },
  {
    "id": 901,
    "e_name": "イベント名",
    "e_genre": "Genre2",
    "o_name": "企画団体名",
    "area": "Area1",
    "p_name": "103"
  },
  {
    "id": 901,
    "e_name": "イベント名",
    "e_genre": "Genre2",
    "o_name": "企画団体名",
    "area": "Area1",
    "p_name": "103"
  },
  {
    "id": 901,
    "e_name": "イベント名",
    "e_genre": "Genre2",
    "o_name": "企画団体名",
    "area": "Area1",
    "p_name": "103"
  },
  {
    "id": 901,
    "e_name": "イベント名",
    "e_genre": "Genre2",
    "o_name": "企画団体名",
    "area": "Area1",
    "p_name": "103"
  }
]
